gpt4api_dg/API.py
gpt4api_dg/__init__.py
gpt4api_dg/models.py
gpt4api_dg-0.0.1.dist-info/LICENSE
gpt4api_dg-0.0.1.dist-info/METADATA
gpt4api_dg-0.0.1.dist-info/WHEEL
gpt4api_dg-0.0.1.dist-info/top_level.txt
gpt4api_dg-0.0.1.dist-info/RECORD
