Metadata-Version: 2.1
Name: gpt4api-dg
Version: 0.0.1
Summary: Wrapper for OpenAI API, intended to be used for a discord bot powered by GPT-4.
Author-email: Ondřej Moravec <moravec@devground.cz>
Project-URL: Homepage, https://github.com/hkcmoris/gpt4api_dg
Project-URL: Bugtracker, https://github.com/hkcmoris/gpt4api_dg/issues
Classifier: Development Status :: 3 - Alpha
Classifier: Intended Audience :: Developers
Classifier: Programming Language :: Python :: 3
Classifier: License :: OSI Approved :: MIT License
Classifier: Operating System :: OS Independent
Classifier: Topic :: Software Development :: Libraries :: Python Modules
Requires-Python: >=3.7
License-File: LICENSE
Requires-Dist: openai
Requires-Dist: requests
